gem_suite/gem_core.abi3.so
gem_suite/gem_core.pyi
gem_suite/analysis.py
gem_suite/plaquettes.py
gem_suite/__init__.py
gem_suite/experiments.py
gem_suite/plot_utils.py
gem_suite/sub_analysis/__init__.py
gem_suite/sub_analysis/magnetization.py
gem_suite/sub_analysis/operators.py
gem_suite-0.1.6.dist-info/RECORD
gem_suite-0.1.6.dist-info/WHEEL
gem_suite-0.1.6.dist-info/top_level.txt
gem_suite-0.1.6.dist-info/LICENSE.txt
gem_suite-0.1.6.dist-info/METADATA
